ttstune/__init__.py
ttstune/cli.py
ttstune-0.1.0.dist-info/licenses/LICENSE.APACHE
ttstune-0.1.0.dist-info/licenses/LICENSE.MIT
ttstune-0.1.0.dist-info/METADATA
ttstune-0.1.0.dist-info/WHEEL
ttstune-0.1.0.dist-info/entry_points.txt
ttstune-0.1.0.dist-info/top_level.txt
ttstune-0.1.0.dist-info/RECORD
