Metadata-Version: 2.4
Name: ttstune
Version: 0.1.0
Summary: Configuration-driven framework for fine-tuning TTS models.
Author-email: mrfakename <me@mrfake.name>
License: MIT OR Apache-2.0
Requires-Python: >=3.9
License-File: LICENSE.APACHE
License-File: LICENSE.MIT
Requires-Dist: click
Provides-Extra: dev
Requires-Dist: ruff; extra == "dev"
Requires-Dist: mypy; extra == "dev"
Requires-Dist: pytest; extra == "dev"
Requires-Dist: pre-commit; extra == "dev"
Dynamic: license-file
